{"filename":"impact-struct-pop-change.pdf","metadata":{"misc":{"custom_properties":["{}"],"dc_rights":["{}"],"dc_description":["{}"],"cache":["{}"],"dc_type":["[]"],"dc_subject":["[]"],"dc_contributor":["[]"],"dc_relation":["[]"],"dc_date":["[]"],"dc_language":["[]"],"dc_publisher":["[]"]},"software":["Acrobat Distiller 9.0.0 (Windows)","PScript5.dll Version 5.2.2"],"date":["2009-08-25T13:14:42+12:00","2009-08-26T14:21:42+12:00"],"people":["LParmint","['LParmint']"]},"filesize_bytes":476913,"children":[{"date":[]},{"date":[]}],"sha1":"68aafed1bee966e82d6fc9e63bbbe567c1f5096a","mimetype":"application/pdf","url":"kiwiblog.co.nz@@http://www.stats.govt.nz/~/media/Statistics/browse-categories/people-and-communities/older-people/structural-change-and-the-65-population/impact-struct-pop-change.pdf"}