{"children":[{"exif:PixelUnit":"1"},{"exif:PixelUnit":"1"}],"filesize_bytes":2470278,"filename":"drinking-water-standards-2008-jun14.pdf","mimetype":"application/pdf","sha1":"8e4317b208387c294614ef7cc161cdb8309902be","metadata":{"xmp":{},"info":{"/CreationDate":"D:20140626153753+12'00'","/Creator":"Microsoft® Word 2010","/Title":"Drinking-water Standards for New Zealand 2005 (Revised 2008)","/Author":"Ministry of Health","/Keywords":"drinking-water,standards,2005,revised 2008,ministry of health,","/Producer":"Microsoft® Word 2010","/ModDate":"D:20140626153753+12'00'"}},"url":"kiwiblog.co.nz@@http://www.health.govt.nz/system/files/documents/publications/drinking-water-standards-2008-jun14.pdf"}