{"children":[{"date":[]},{"date":[]},{"date":[]},{"date":[]},{"date":[]},{"date":[]}],"filesize_bytes":1224701,"metadata":{"date":["2013-06-04T14:10:24+12:00","2013-06-05T10:34:52+12:00"],"software":["Acrobat PDFMaker 10.0 for Word","Adobe PDF Library 10.0"],"misc":{"cache":["{}"],"dc_date":["[]"],"dc_subject":["[]"],"dc_language":["[]"],"dc_contributor":["[]"],"dc_relation":["[]"],"dc_type":["[]"],"dc_publisher":["[]"],"dc_rights":["{}"]},"people":["Megan Harrison","['Megan Harrison']"]},"filename":"Electricity2.pdf","sha1":"31a87c3c228d04412b5dc44af6cfab26775982bf","mimetype":"application/pdf","url":"kiwiblog.co.nz@@http://media.nzherald.co.nz/webcontent/document/pdf/201323/Electricity2.pdf"}