{"filesize_bytes":134539,"filename":"27.jpg","mimetype":"image/jpeg","sha1":"5daa7258b810272deae8e156389b615dbee985b7","metadata":{"exif:PhotometricInterpretation":"2","icc:description":"Generic RGB Profile","exif:Software":"Adobe Photoshop CC 2014 (Macintosh)","exif:BitsPerSample":"8, 8, 8","exif:SamplesPerPixel":"3","icc:manufacturer":"Generic RGB Profile","exif:DateTime":"2015:01:20 12:33:20","icc:copyright":"Copyright 2007 Apple Inc., all rights reserved.","icc:model":"Generic RGB Profile"},"url":"kiwiblog.co.nz@@http://www.art-agenda.com/wp-content/uploads/2015/01/27.jpg"}