{"mimetype":"image/jpeg","sha1":"af695db08cda4916b87f081947fafb0c72e3a63c","filename":"smith-kitchener.jpg","metadata":{"misc":{"icc:copyright":["Copyright 1999 Adobe Systems Incorporated"],"exif:thumbnail:Compression":["6"],"icc:model":["Dot Gain 20%"],"exif:Software":["Adobe Photoshop CS3 Macintosh"],"icc:manufacturer":["Dot Gain 20%"],"icc:description":["Dot Gain 20%"],"exif:thumbnail:YResolution":["72/1"],"exif:thumbnail:XResolution":["72/1"],"exif:thumbnail:ResolutionUnit":["2"],"exif:thumbnail:JPEGInterchangeFormat":["302"]},"date":["2017-05-08 11:36:17","2000-02-01 05:03:01"]},"filesize_bytes":80300,"url":"whaleoil.co.nz@@http://www.whaleoil.co.nz/images/2010/05/smith-kitchener.jpg"}