{"filename":"Women_positive_Koran.pdf","mimetype":"application/pdf","filesize_bytes":62348,"sha1":"695e0369cbea9a9db9bd0ee40f361f27a78472cf","metadata":{"info":{"/Producer":"Mac OS X 10.7.5 Quartz PDFContext","/Author":"Brian Kelly","/Title":"Microsoft Word - Women_positive_Koran.docx","/AAPL:Keywords":[],"/Creator":"Word","/CreationDate":"D:20141108205312Z00'00'","/Keywords":"","/ModDate":"D:20141108205312Z00'00'"},"xmp":{}},"url":"whaleoil.co.nz@@http://www.cspipublishing.com/statistical/TrilogyStats/Koran/Women_positive_Koran.pdf"}