{"mimetype":"image/jpeg","filename":"5389944146_c04a6569e4_o1.jpg","filesize_bytes":1885485,"sha1":"55c4f54ee0d6020f991b5036f731f23f0112a335","metadata":{"software":["Group of Men. New York. Photo: Jacob Riis","NIKON CORPORATION","NIKON D3X"],"misc":{"xapMM:InstanceID":["uuid:D201605B1522E011BD7DDA2AC5F8B6F7"],"crs:AlreadyApplied":["True"],"exif:Software":["Adobe Photoshop Elements 3.0 Windows"],"exif:DigitalZoomRatio":["1/1"],"exif:thumbnail:Compression":["6"],"exif:thumbnail:ResolutionUnit":["2"],"exif:RedEyeMode":["False"],"exif:YCbCrCoefficients":["299/1000, 587/1000, 114/1000"],"exif:Contrast":["0"],"photoshop:ColorMode":["3"],"icc:model":["Nikon Adobe RGB 4.0.0.3001"],"exif:Return":["0"],"exif:SensingMethod":["2"],"tiff:Model":["NIKON D3X"],"photoshop:LegacyIPTCDigest":["0DC0083CDFBC14A02B86937E786BE86B"],"exif:SubjectDistanceRange":["0"],"exif:DateTimeOriginal":["2011-01-14T11:02:40+12:00"],"exif:FileSource":["3"],"exif:PrimaryChromaticities":["64/100, 33/100, 21/100, 71/100, 15/100, 6/100"],"exif:SamplesPerPixel":["3"],"exif:Saturation":["0"],"exif:Gamma":["22/10"],"exif:PlanarConfiguration":["1"],"exif:Fired":["False"],"icc:description":["Nikon Adobe RGB 4.0.0.3001"],"icc:copyright":["Nikon Inc. & Nikon Corporation 2009"],"exif:DateTimeDigitized":["2011-01-14T11:02:40+12:00"],"xap:CreatorTool":["Adobe Photoshop Elements 3.0 Windows"],"xap:MetadataDate":["2016-05-10T11:30:48+12:00"],"exif:Artist":["                                    "],"exif:thumbnail:JPEGInterchangeFormat":["1394"],"exif:FlashpixVersion":["0100"],"tiff:SamplesPerPixel":["3"],"xap:ModifyDate":["2016-05-10T11:30:48+12:00"],"exif:PhotometricInterpretation":["2"],"exif:thumbnail:YResolution":["72/1"],"xap:CreateDate":["2011-01-17T09:39:54+01:00"],"exif:DateTime":["2016:05:10 11:30:48"],"exif:BitsPerSample":["16, 16, 16"],"tiff:Compression":["1"],"tiff:PhotometricInterpretation":["2"],"exif:GainControl":["0"],"exif:WhitePoint":["313/1000, 329/1000"],"exif:Sharpness":["0"],"exif:Copyright":["                                                      "],"exif:GPSInfo":["1280"],"exif:Mode":["0"],"exif:UserComment":["65, 83, 67, 73, 73, 0, 0, 0, 32, 32, 32, 32, 32, 32, 32, 32, 32, 32, 32, 32, 32, 32, 32, 32, 32, 32, 32, 32, 32, 32, 32, 32, 32, 32, 32, 32, 32, 32, 32, 32, 32, 32, 32, 32"],"exif:thumbnail:XResolution":["72/1"],"exif:GPSVersionID":["2.2.0.0"],"tiff:Make":["NIKON CORPORATION"],"xapMM:PreservedFileName":["Img0690.jpg"],"exif:Function":["False"],"photoshop:ICCProfile":["Nikon Adobe RGB 4.0.0.3001"],"exif:CFAPattern":["0, 2, 0, 2, 0, 1, 1, 2"],"tiff:PlanarConfiguration":["1"],"xapMM:DocumentID":["uuid:18AE79371522E011BD7DDA2AC5F8B6F7"],"stRef:instanceID":["uuid:15AE79371522E011BD7DDA2AC5F8B6F7"],"exif:ReferenceBlackWhite":["0/1, 255/1, 0/1, 255/1, 0/1, 255/1"],"exif:SceneType":["1"],"icc:manufacturer":["Nikon Adobe RGB 4.0.0.3001"]},"date":["2000-07-30T00:00:00","2011-01-14T11:02:40","2011-01-14T11:02:40+12:00","2011-01-17T09:39:54","2016-05-10T11:30:48","2017-05-08T10:09:32"],"ascii":{"exif:UserComment->ASCII":["ASCII"]}},"url":"whaleoil.co.nz@@http://www.whaleoil.co.nz/wp-content/uploads/2016/05/5389944146_c04a6569e4_o1.jpg"}