{"metadata":{"misc":{"tiff:Compression":["1"],"exif:thumbnail:YResolution":["72/1"],"tiff:ImageLength":["2010"],"exif:SamplesPerPixel":["1"],"exif:Software":["Adobe Photoshop Elements 3.0 Windows"],"tiff:PhotometricInterpretation":["1"],"xapMM:DocumentID":["adobe:docid:photoshop:975133f7-090a-11e7-b6bc-e149f2219ab2"],"exif:RowsPerStrip":["2010"],"exif:thumbnail:JPEGInterchangeFormat":["574"],"xap:CreatorTool":["Adobe Photoshop Elements 3.0 Windows"],"exif:thumbnail:Compression":["6"],"unknown":["0"],"xap:CreateDate":["2017-03-15T11:04:32+12:00"],"exif:StripByteCounts":["7173690"],"xap:MetadataDate":["2017-03-15T12:05:03+12:00"],"exif:thumbnail:ResolutionUnit":["2"],"exif:PhotometricInterpretation":["1"],"xap:ModifyDate":["2017-03-15T12:05:03+12:00"],"exif:BitsPerSample":["8"],"exif:thumbnail:XResolution":["72/1"],"tiff:SamplesPerPixel":["1"]},"software":["People came from near and far to watch as police investigated these horrific crimes."],"date":["2010-07-30T00:00:00","2017-03-15T11:04:32","2017-03-15T12:05:03"]},"filename":"belle-gunness-20.jpg","mimetype":"image/jpeg","filesize_bytes":386009,"sha1":"99354cd0fc47f0d6728fd97313a1cf41843cc37a","url":"whaleoil.co.nz@@http://www.whaleoil.co.nz/wp-content/uploads/2017/03/belle-gunness-20.jpg"}