{"filesize_bytes":87381,"sha1":"422338cef5d030fb3ed0e49dcac85d1e64b8783c","metadata":{"ascii":{"exif:UserComment->ASCII":["ASCIIUser comments"]},"misc":{"exif:thumbnail:ImageWidth":["320"],"exif:DateTime":["2013:02:26 08:27:58"],"exif:Software":["I9100XWLPT"],"exif:thumbnail:Compression":["6"],"exif:DateTimeOriginal":["2013:02:26 08:27:58"],"exif:thumbnail:YResolution":["72/1"],"exif:MakerNote":["5, 0, 1, 0, 7, 0, 4, 0, 0, 0, 48, 49, 48, 48, 2, 0, 4, 0, 1, 0, 0, 0, 0, 32, 1, 0, 64, 0, 4, 0, 1, 0, 0, 0, 0, 0, 0, 0, 80, 0, 4, 0, 1, 0, 0, 0, 1, 0, 0, 0, 0, 1, 3, 0, 1, 0, 0, 0, 0, 0, 0, 0, 0, 0, 0, 0"],"exif:thumbnail:JPEGInterchangeFormat":["860"],"exif:thumbnail:Orientation":["1"],"exif:DateTimeDigitized":["2013:02:26 08:27:58"],"exif:thumbnail:XResolution":["72/1"],"exif:BrightnessValue":["1064/100"],"exif:thumbnail:ImageLength":["240"],"exif:thumbnail:ResolutionUnit":["2"],"exif:ImageUniqueID":["ONEF01"],"exif:UserComment":["65, 83, 67, 73, 73, 0, 0, 0, 85, 115, 101, 114, 32, 99, 111, 109, 109, 101, 110, 116, 115"],"exif:thumbnail:JPEGInterchangeFormatLength":["36088"]},"software":["GT-I9100","SAMSUNG"],"date":["2013-02-26T08:27:58","2017-05-08T09:38:12"]},"filename":"20130226_0827581-630x472.jpeg","mimetype":"image/jpeg","url":"whaleoil.co.nz@@http://www.whaleoil.co.nz/wp-content/uploads/2013/02/20130226_0827581-630x472.jpeg"}