{"mimetype":"image/jpeg","sha1":"f7d303e38c0444a8912d817c9f3c2e4058e338c2","filename":"bielski-partisan-.jpg","metadata":{"misc":{"exif:thumbnail:Compression":["6"],"xapMM:DocumentID":["adobe:docid:photoshop:6fb986d0-22fa-11e7-9504-af03b67fb9b8"],"exif:Software":["Adobe Photoshop Elements 3.0 Windows"],"icc:model":["Adobe RGB (1998)"],"exif:ImageDescription":["The Legacy of the Bielski Brothers. The heroic efforts of three brothers who helped save more than 1,200 people while living in the forest during World War II. Florida Holocaust Museum. "],"exif:thumbnail:YResolution":["72/1"],"icc:copyright":["Copyright (c) 1999 Adobe Systems Incorporated. All Rights Reserved."],"xap:ModifyDate":["2017-04-17T11:16:38+12:00"],"xap:CreatorTool":["Adobe Photoshop Elements 3.0 Windows"],"xap:CreateDate":["2017-04-17T11:13:58+12:00"],"icc:manufacturer":["Adobe RGB (1998)"],"icc:description":["Adobe RGB (1998)"],"xap:MetadataDate":["2017-04-17T11:16:38+12:00"],"exif:thumbnail:XResolution":["72/1"],"exif:thumbnail:ResolutionUnit":["2"],"exif:thumbnail:JPEGInterchangeFormat":["510"]},"date":["2017-05-08 10:42:35","7041-02-01 07:00:00","2017-04-17 11:13:58","2017-04-17 11:16:38"]},"filesize_bytes":526963,"url":"whaleoil.co.nz@@https://www.whaleoil.co.nz/wp-content/uploads/2017/04/bielski-partisan-.jpg"}