{"mimetype":"image/jpeg","sha1":"2619a7a988abae2bd708ace414e23927bdaa4f27","filename":"unnamed-4.jpg","metadata":{"misc":{"icc:manufacturer":["IEC http://www.iec.ch"],"icc:description":["sRGB IEC61966-2.1"],"icc:model":["IEC 61966-2.1 Default RGB colour space - sRGB"],"icc:copyright":["Copyright (c) 1998 Hewlett-Packard Company"],"exif:Software":["Picasa"]},"date":["2017-05-08 19:49:02"]},"filesize_bytes":48428,"url":"whaleoil.co.nz@@http://www.whaleoil.co.nz/wp-content/uploads/2015/05/unnamed-4.jpg"}