{"filename":"6b2edc93a982e6404f5b6d3afaba673f.jpg","mimetype":"image/jpeg","filesize_bytes":155879,"sha1":"c21df586eeb48609ef0263f291594f076e4deb8b","metadata":{"misc":{"exif:thumbnail:XResolution":["72/1"],"exif:thumbnail:ResolutionUnit":["2"],"exif:Software":["Adobe Photoshop Elements 3.0 Windows"],"exif:thumbnail:Compression":["6"],"icc:description":["Adobe RGB (1998)"],"xapMM:DocumentID":["adobe:docid:photoshop:123838ad-4e33-11e7-a671-b7f5a0cf714f"],"icc:copyright":["Copyright (c) 1999 Adobe Systems Incorporated. All Rights Reserved."],"icc:manufacturer":["Adobe RGB (1998)"],"xap:MetadataDate":["2017-06-11T11:45:50+12:00"],"exif:thumbnail:JPEGInterchangeFormat":["350"],"icc:model":["Adobe RGB (1998)"],"xap:CreatorTool":["Adobe Photoshop Elements 3.0 Windows"],"xap:ModifyDate":["2017-06-11T11:45:50+12:00"],"exif:thumbnail:YResolution":["72/1"],"xap:CreateDate":["2017-06-11T11:44:42+12:00"]},"date":["2017-06-11T11:44:42","2017-06-11T11:45:50"],"software":["Benjamin \"Lefty\" Ruggiero."]},"url":"whaleoil.co.nz@@https://www.whaleoil.co.nz/wp-content/uploads/2017/06/6b2edc93a982e6404f5b6d3afaba673f.jpg"}