{"filesize_bytes":300327,"metadata":{"date":["2016-03-13T10:49:25","2016-03-13T11:56:04"],"misc":{"xap:ModifyDate":["2016-03-13T11:56:04+12:00"],"icc:copyright":["Copyright (c) 1999 Adobe Systems Incorporated. All Rights Reserved."],"exif:thumbnail:JPEGInterchangeFormat":["310"],"xap:CreateDate":["2016-03-13T10:49:25+12:00"],"exif:DateTime":["2016:03:13 11:56:04"],"icc:description":["Adobe RGB (1998)"],"icc:model":["Adobe RGB (1998)"],"xap:MetadataDate":["2016-03-13T11:56:04+12:00"],"exif:thumbnail:ResolutionUnit":["2"],"exif:thumbnail:XResolution":["72/1"],"xap:CreatorTool":["Adobe Photoshop Elements 3.0 Windows"],"exif:thumbnail:YResolution":["72/1"],"icc:manufacturer":["Adobe RGB (1998)"],"exif:Software":["Adobe Photoshop Elements 3.0 Windows"],"xapMM:DocumentID":["adobe:docid:photoshop:87290ff8-e8a5-11e5-9fdf-e0b02e672a44"],"exif:thumbnail:Compression":["6"]}},"sha1":"1eb763b833e75b49739e5f39e08039a64e99a514","mimetype":"image/jpeg","filename":"Brianna.jpg","url":"whaleoil.co.nz@@http://www.whaleoil.co.nz/wp-content/uploads/2016/03/Brianna.jpg"}