{"mimetype":"image/jpeg","sha1":"f40c0697bef54ff0c09558289b4906b4d9739523","filename":"000030b8_big.jpg","metadata":{"misc":{"exif:thumbnail:Compression":["6"],"xapMM:DocumentID":["adobe:docid:photoshop:8b8bd177-26e2-11e7-8576-80a539a2a92a"],"exif:Software":["Adobe Photoshop Elements 3.0 Windows"],"exif:ImageDescription":["Benito Mussolini going for a drive with his pet lion cub [Ras], a gift from Aldo Finci. (Photo by Keystone/Getty Images)"],"exif:thumbnail:YResolution":["72/1"],"xap:ModifyDate":["2017-04-22T10:36:19+12:00"],"xap:CreatorTool":["Adobe Photoshop Elements 3.0 Windows"],"xap:CreateDate":["2017-04-22T10:35:59+12:00"],"xap:MetadataDate":["2017-04-22T10:36:19+12:00"],"exif:thumbnail:XResolution":["72/1"],"exif:thumbnail:ResolutionUnit":["2"],"exif:thumbnail:JPEGInterchangeFormat":["442"]},"date":["2017-05-08 11:08:34","7042-02-01 02:00:00","2017-04-22 10:35:59","2017-04-22 10:36:19"]},"filesize_bytes":204396,"url":"whaleoil.co.nz@@https://www.whaleoil.co.nz/wp-content/uploads/2017/04/000030b8_big.jpg"}