{"mimetype":"image/jpeg","sha1":"cc0941536e0aa5c6ecfe01ff9efefd11cd1abedb","filename":"Grave.jpg","metadata":{"misc":{"exif:thumbnail:Compression":["6"],"exif:Fired":["False"],"exif:Software":["Adobe Photoshop Elements 3.0 Windows"],"exif:Saturation":["0"],"exif:GainControl":["0"],"exif:ImageDescription":["Grave of Henry McCarty (aka Billy the Kid). Why the big cage, akin to something they use in WWF? It turns out that the real headstone had been stolen three times, the first time back in 1950. It stayed missing for 26 years, before it was found in Granbury, TX (a town once filled with aging outlaws whose deaths were faked). Then it got swiped in 1981, recovered a week later in Huntington Beach, CA, and vamoosed again more recently."],"exif:FlashpixVersion":["0100"],"icc:copyright":["Copyright (c) 1999 Adobe Systems Incorporated. All Rights Reserved."],"xap:ModifyDate":["2016-05-16T11:43:57+12:00"],"exif:thumbnail:YResolution":["72/1"],"exif:Mode":["3"],"tiff:Make":["OLYMPUS IMAGING CORP.  "],"xap:CreateDate":["0-00-00T00:00:00+12:00"],"icc:manufacturer":["Adobe RGB (1998)"],"tiff:YCbCrPositioning":["2"],"tiff:Model":["u40D,S500,uD500 "],"exif:FileSource":["3"],"exif:Contrast":["0"],"xap:MetadataDate":["2016-05-16T11:43:57+12:00"],"xapMM:DocumentID":["adobe:docid:photoshop:6ba3f30a-1af6-11e6-93eb-ae75c9df7780"],"icc:model":["Adobe RGB (1998)"],"exif:DateTimeDigitized":["0-00-00T00:00:00+12:00"],"exif:UserComment":["0, 0, 0, 0, 0, 0, 0, 0, 32, 32, 32, 32, 32, 32, 32, 32, 32, 32, 32, 32, 32, 32, 32, 32, 32, 32, 32, 32, 32, 32, 32, 32, 32, 32, 32, 32, 32, 32, 32, 32, 32, 32, 32, 32, 32, 32, 32, 32, 32, 32, 32, 32, 32, 32, 32, 32, 32, 32, 32, 32, 32, 32, 32, 32, 32, 32, 32, 32, 32, 32, 32, 32, 32, 32, 32, 32, 32, 32, 32, 32, 32, 32, 32, 32, 32, 32, 32, 32, 32, 32, 32, 32, 32, 32, 32, 32, 32, 32, 32, 32, 32, 32, 32, 32, 32, 32, 32, 32, 32, 32, 32, 32, 32, 32, 32, 32, 32, 32, 32, 32, 32, 32, 32, 32, 32"],"exif:Function":["False"],"exif:Make":["OLYMPUS IMAGING CORP.  "],"exif:Sharpness":["0"],"exif:RedEyeMode":["False"],"xap:CreatorTool":["Adobe Photoshop Elements 3.0 Windows"],"exif:Return":["0"],"exif:PrintImageMatching":["80, 114, 105, 110, 116, 73, 77, 0, 48, 51, 48, 48, 0, 0, 37, 0, 1, 0, 20, 0, 20, 0, 2, 0, 1, 0, 0, 0, 3, 0, 240, 0, 0, 0, 7, 0, 0, 0, 0, 0, 8, 0, 0, 0, 0, 0, 9, 0, 0, 0, 0, 0, 10, 0, 0, 0, 0, 0, 11, 0, 56, 1, 0, 0, 12, 0, 0, 0, 0, 0, 13, 0, 0, 0, 0, 0, 14, 0, 80, 1, 0, 0, 16, 0, 96, 1, 0, 0, 32, 0, 180, 1, 0, 0, 0, 1, 3, 0, 0, 0, 1, 1, 255, 0, 0, 0, 2, 1, 131, 0, 0, 0, 3, 1, 131, 0, 0, 0, 4, 1, 131, 0, 0, 0, 5, 1, 131, 0, 0, 0, 6, 1, 131, 0, 0, 0, 7, 1, 128, 128, 128, 0, 16, 1, 128, 0, 0, 0, 0, 2, 0, 0, 0, 0, 7, 2, 0, 0, 0, 0, 8, 2, 0, 0, 0, 0, 9, 2, 0, 0, 0, 0, 10, 2, 0, 0, 0, 0, 11, 2, 248, 1, 0, 0, 13, 2, 0, 0, 0, 0, 32, 2, 214, 1, 0, 0, 0, 3, 3, 0, 0, 0, 1, 3, 255, 0, 0, 0, 2, 3, 131, 0, 0, 0, 3, 3, 131, 0, 0, 0, 6, 3, 131, 0, 0, 0, 16, 3, 128, 0, 0, 0, 0, 4, 0, 0, 0, 0, 0, 0, 9, 17, 0, 0, 16, 39, 0, 0, 11, 15, 0, 0, 16, 39, 0, 0, 151, 5, 0, 0, 16, 39, 0, 0, 176, 8, 0, 0, 16, 39, 0, 0, 1, 28, 0, 0, 16, 39, 0, 0, 94, 2, 0, 0, 16, 39, 0, 0, 139, 0, 0, 0, 16, 39, 0, 0, 203, 3, 0, 0, 16, 39, 0, 0, 229, 27, 0, 0, 16, 39, 0, 0, 0, 0, 0, 0, 0, 0, 0, 0, 0, 0, 0, 0, 0, 0, 0, 0, 0, 0, 0, 0, 0, 0, 0, 0, 0, 0, 0, 0, 0, 0, 0, 0, 0, 0, 0, 0, 0, 0, 0, 0, 4, 0, 0, 0, 0, 0, 0, 0, 0, 0, 0, 0, 0, 0, 0, 0, 0, 0, 0, 0, 0, 0, 0, 0, 0, 0, 0, 0, 0, 0, 0, 0, 0, 0, 0, 0, 0, 0, 0, 0, 0, 0, 0, 0, 0, 0, 0, 0, 0, 0, 0, 0, 0, 0, 0, 0, 0, 0, 0, 0, 0, 0, 0, 0, 0, 0, 0, 0, 0, 0, 0, 0, 0, 0, 0, 0, 0, 0, 0, 0, 0, 0, 0, 0, 5, 5, 5, 0, 0, 0, 64, 64, 128, 128, 192, 192, 255, 255, 0, 0, 64, 64, 128, 128, 192, 192, 255, 255, 0, 0, 64, 64, 128, 128, 192, 192, 255, 255, 5, 5, 5, 0, 0, 0, 64, 64, 128, 128, 192, 192, 255, 255, 0, 0, 64, 64, 128, 128, 192, 192, 255, 255, 0, 0, 64, 64, 128, 128, 192, 192, 255, 255, 0, 0, 0, 0, 0, 0, 0, 0, 0, 0, 0, 0, 0, 0, 0, 0, 0, 0, 0, 0, 0, 0, 0, 0"],"icc:description":["Adobe RGB (1998)"],"exif:DigitalZoomRatio":["100/100"],"exif:thumbnail:XResolution":["72/1"],"exif:thumbnail:ResolutionUnit":["2"],"exif:thumbnail:JPEGInterchangeFormat":["1898"]},"ascii":{"exif:PrintImageMatching->ASCII":["PrintIM0300%8P`  '''''^''''@@@@@@@@@@@@"]},"date":["2017-05-08 20:09:12","6051-02-01 06:00:00","0-00-00T00:00:00+12:00","2000-05-08 00:00:00","2016-05-16 11:43:57"],"software":["u40D,S500,uD500 "]},"filesize_bytes":2740728,"url":"whaleoil.co.nz@@http://www.whaleoil.co.nz/wp-content/uploads/2016/05/Grave.jpg"}