{"sha1":"f8518753fb2b82c099b6db44199aee41464fa80c","filename":"Screen-Shot-2014-09-19-at-9.47.02-pm-630x371.png","filesize_bytes":209260,"metadata":{"date":[],"misc":{"icc:manufacturer":["Display"],"icc:model":["Display"],"icc:description":["Display"],"png:text":["2 tEXt/zTXt/iTXt chunks were found"],"icc:copyright":["Copyright Apple Inc., 2014"]}},"mimetype":"image/png","url":"whaleoil.co.nz@@http://www.whaleoil.co.nz/wp-content/uploads/2014/09/Screen-Shot-2014-09-19-at-9.47.02-pm-630x371.png"}