{"mimetype":"image/jpeg","sha1":"9dd7df3f4aeff0ab379693bfba02e6fd686eb03c","filename":"cullen-2.jpg","metadata":{"misc":{"exif:thumbnail:Compression":["6"],"xapMM:DocumentID":["adobe:docid:photoshop:3a74fb64-0d99-11e6-94bd-905251feb46c"],"exif:Software":["Adobe Photoshop Elements 3.0 Windows"],"icc:model":["Adobe RGB (1998)"],"exif:ImageDescription":["First claim: In an interview to be with CBS', Charles Cullen at first says he thought he was helping people by ending their suffering..."],"exif:thumbnail:YResolution":["72/1"],"icc:copyright":["Copyright (c) 1999 Adobe Systems Incorporated. All Rights Reserved."],"xap:ModifyDate":["2016-04-29T11:52:26+12:00"],"xap:CreatorTool":["Adobe Photoshop Elements 3.0 Windows"],"photoshop:Credit":["© AP"],"xap:CreateDate":["2016-04-29T11:31:28+12:00"],"icc:manufacturer":["Adobe RGB (1998)"],"icc:description":["Adobe RGB (1998)"],"xap:MetadataDate":["2016-04-29T11:52:26+12:00"],"exif:thumbnail:XResolution":["72/1"],"exif:thumbnail:ResolutionUnit":["2"],"exif:thumbnail:JPEGInterchangeFormat":["458"]},"date":["2017-05-08 11:02:20","6042-02-01 09:00:00","2016-04-29 11:31:28","2016-04-29 11:52:26"]},"filesize_bytes":399106,"url":"whaleoil.co.nz@@http://www.whaleoil.co.nz/wp-content/uploads/2016/04/cullen-2.jpg"}