{"filename":"DEC-24-JIB-Intercept.pdf","filesize_bytes":3062548,"children":[{"icc:manufacturer":"IEC http://www.iec.ch","unknown":"Apple Mac OS X","icc:model":"IEC 61966-2.1 Default RGB colour space - sRGB","exif:Make":"Canon","icc:description":"sRGB IEC61966-2.1","exif:Model":"MP490 series","icc:copyright":"Copyright (c) 1998 Hewlett-Packard Company","exif:Software":"Apple Image Capture"},{"icc:manufacturer":"IEC http://www.iec.ch","unknown":"Apple Mac OS X","icc:model":"IEC 61966-2.1 Default RGB colour space - sRGB","exif:Make":"Canon","icc:description":"sRGB IEC61966-2.1","exif:Model":"MP490 series","icc:copyright":"Copyright (c) 1998 Hewlett-Packard Company","exif:Software":"Apple Image Capture"},{"icc:manufacturer":"IEC http://www.iec.ch","unknown":"Apple Mac OS X","icc:model":"IEC 61966-2.1 Default RGB colour space - sRGB","exif:Make":"Canon","icc:description":"sRGB IEC61966-2.1","exif:Model":"MP490 series","icc:copyright":"Copyright (c) 1998 Hewlett-Packard Company","exif:Software":"Apple Image Capture"},{"icc:manufacturer":"IEC http://www.iec.ch","unknown":"Apple Mac OS X","icc:model":"IEC 61966-2.1 Default RGB colour space - sRGB","exif:Make":"Canon","icc:description":"sRGB IEC61966-2.1","exif:Model":"MP490 series","icc:copyright":"Copyright (c) 1998 Hewlett-Packard Company","exif:Software":"Apple Image Capture"}],"metadata":{"info":{"/CreationDate":"D:20141230234528Z00'00'","/Producer":"Mac OS X 10.9.5 Quartz PDFContext","/ModDate":"D:20141230234528Z00'00'"},"xmp":{}},"sha1":"3f9d81318fc7ee64e7b40f39ca718f97e394d0bd","mimetype":"application/pdf","url":"whaleoil.co.nz@@https://prod01-cdn03.cdn.firstlook.org/wp-uploads/sites/1/2014/12/DEC-24-JIB-Intercept.pdf"}