{"mimetype":"image/jpeg","metadata":{"date":["2000-02-01T04:01:09","2009-04-28T00:00:00","2009-04-28T11:02:42","2016-06-29T19:14:20"],"misc":{"icc:copyright":["Copyright Apple, Inc., 2010"],"exif:DateTime":["2010:04:19 08:34:26"],"exif:Software":["QuickTime 7.6.6"],"icc:manufacturer":["Display"],"icc:model":["Display"],"exif:DateTimeOriginal":["2009:04:28 11:02:42"],"unknown":["Mac OS X 10.6.3"],"icc:description":["Display"]}},"sha1":"372d7404fca36054cfc9676b1fa9004e909fea2d","filesize_bytes":100037,"filename":"Auckland-city-scene-cropped-2.jpg","url":"whaleoil.co.nz@@http://i1.wp.com/www.whaleoil.co.nz/wp-content/uploads/2014/02/Auckland-city-scene-cropped-2.jpg"}