{"mimetype":"image/jpeg","sha1":"2e45d9ce142f874a0df56317cbe40fb3fb1d7fae","filename":"Mens-Breast-Cancer.jpg","filesize_bytes":116705,"metadata":{"date":["2017-07-24 16:01:37","4031-02-01 02:00:00"],"misc":{"exif:Software":["Adobe Photoshop Elements 3.0 Windows"],"icc:copyright":["Copyright International Color Consortium, 2009"],"exif:thumbnail:Compression":["6"],"exif:DateTime":["2014:03:12 13:42:08"],"icc:manufacturer":["sRGB IEC61966-2-1 black scaled"],"exif:thumbnail:ResolutionUnit":["2"],"icc:description":["sRGB IEC61966-2-1 black scaled"],"exif:thumbnail:XResolution":["72/1"],"icc:model":["IEC 61966-2-1 Default RGB Colour Space - sRGB"],"exif:thumbnail:YResolution":["72/1"],"exif:thumbnail:JPEGInterchangeFormat":["310"]}},"url":"whaleoil.co.nz@@https://i2.wp.com/www.whaleoil.co.nz/wp-content/uploads/2014/03/Mens-Breast-Cancer.jpg"}